BigCatfish/test1.py
BigCatfish/test2.py
BigCatfish-0.0.0.2.dist-info/METADATA
BigCatfish-0.0.0.2.dist-info/WHEEL
BigCatfish-0.0.0.2.dist-info/top_level.txt
BigCatfish-0.0.0.2.dist-info/RECORD
