Metadata-Version: 2.1
Name: BigCatfish
Version: 0.0.0.2
Summary: My First Test Package
Home-page: https://namu.wiki/w/%EB%84%88%EA%B5%AC%EB%A6%AC
Author-email: gimgemi123@gmail.com
License: MIT
Platform: UNKNOWN
Requires-Python: >=3
